xivapi_beta/__init__.py
xivapi_beta/_wrapper.py
xivapi_beta/client.py
xivapi_beta/exceptions.py
xivapi_beta/endpoints/__init__.py
xivapi_beta/endpoints/asset.py
xivapi_beta/endpoints/item.py
xivapi_beta/endpoints/search.py
xivapi_beta/endpoints/sheet.py
xivapi_beta-0.1.3.dist-info/METADATA
xivapi_beta-0.1.3.dist-info/WHEEL
xivapi_beta-0.1.3.dist-info/RECORD
