Metadata-Version: 2.4
Name: xivapi-beta
Version: 0.1.3
Summary: An asynchronous python wrapper for the XIV API's beta endpoints
Requires-Python: >=3.13
Requires-Dist: aiohttp>=3.11.11
Requires-Dist: async-property>=0.2.2
Provides-Extra: dev
Requires-Dist: aioresponses>=0.7.7; extra == 'dev'
Requires-Dist: mypy>=1.14.1; extra == 'dev'
Requires-Dist: pytest-asyncio>=0.25.0; extra == 'dev'
Requires-Dist: pytest-cov>=6.0.0; extra == 'dev'
Requires-Dist: pytest-coverage>=0.0; extra == 'dev'
Requires-Dist: pytest-mock>=3.14.0; extra == 'dev'
Requires-Dist: pytest>=8.3.4; extra == 'dev'
